{
	"groups":[{
			"keys":"Dragon_json,Dragon_png,fnt_fnt,fight_bg_jpg,test_json,test_txt,test_xml,spriteSheet_json",
			"name":"all"
		}],
	"resources":[
		{
			"name":"Dragon_json",
			"type":"json",
			"url":"assets/Dragon/Dragon.json"
		},
		{
			"name":"Dragon_png",
			"type":"image",
			"url":"assets/Dragon/Dragon.png"
		},
		{
			"name":"fnt_fnt",
			"type":"font",
			"url":"assets/fnt/fnt.fnt"
		},
		{
			"name":"fight_bg_jpg",
			"type":"image",
			"url":"assets/jpg/fight_bg.jpg"
		},
		{
			"name":"test_json",
			"type":"json",
			"url":"assets/myJson/test.json"
		},
		{
			"name":"test_txt",
			"type":"text",
			"url":"assets/myTxt/test.txt"
		},
		{
			"name":"test_xml",
			"type":"xml",
			"url":"assets/myXml/test.xml"
		},
		{
			"name":"spriteSheet_json",
			"subkeys":"bullet_png,p2_btn_png,submit_png",
			"type":"sheet",
			"url":"assets/spritesheet/spriteSheet.json"
		}
	]
}